typer_invoke/__init__.py
typer_invoke/invoke.py
typer_invoke/logging_invoke.py
typer_invoke/py.typed
typer_invoke/pyproject.py
typer_invoke/typer_docs.py
typer_invoke-0.4.0.dist-info/entry_points.txt
typer_invoke-0.4.0.dist-info/licenses/LICENSE.txt
typer_invoke-0.4.0.dist-info/WHEEL
typer_invoke-0.4.0.dist-info/METADATA
typer_invoke-0.4.0.dist-info/RECORD
