Metadata-Version: 2.4
Name: typer-invoke
Version: 0.4.0
Summary: Simplified invocation of typer apps from any directory.
Author: Joao Coelho
Requires-Python: >=3.10
Classifier: License :: OSI Approved :: MIT License
Classifier: Framework :: Pytest
Classifier: Intended Audience :: Developers
Classifier: Programming Language :: Python
Classifier: Development Status :: 4 - Beta
License-File: LICENSE.txt
Requires-Dist: rich
Requires-Dist: typer
Requires-Dist: tomli;python_version<="3.10"
Project-URL: Home, https://github.com/joaonc/typer-invoke
